nextperm/__init__.py
nextperm/core.py
nextperm-0.1.1.dist-info/METADATA
nextperm-0.1.1.dist-info/WHEEL
nextperm-0.1.1.dist-info/top_level.txt
nextperm-0.1.1.dist-info/RECORD
