Metadata-Version: 2.4
Name: nextperm
Version: 0.1.1
Summary: A Python library for next permutation and combinatorial utilities inspired by C++ STL and Java Collections.
Home-page: https://github.com/YD09/nextPerm
Author: Yash Dhake ,Sayali Varkhade
Author-email: dhakeyash123@gmail.com , varkhadesayali@gmail.com
Classifier: Programming Language :: Python :: 3
Classifier: License :: OSI Approved :: MIT License
Classifier: Operating System :: OS Independent
Classifier: Topic :: Software Development :: Libraries :: Python Modules
Requires-Python: >=3.6
Dynamic: author
Dynamic: author-email
Dynamic: classifier
Dynamic: description
Dynamic: description-content-type
Dynamic: home-page
Dynamic: requires-python
Dynamic: summary
